ch01/rtl/greater_than_2bit.v
module greater_than_2bit (
    input [1:0] a,b,
    output agb
);
    assign agb = (a[1] & ~b[1]) | ((a[0] & ~b[0]) & (~(a[1] ^ b[1])));
endmodule

ch01/tb/greater_than_2bit_tb.v
`timescale 1ns / 1ps
module greater_than_2bit_tb (
);
    reg [1:0] a, b;
    wire agb;

    reg expected_agb;
    integer i, j;
    integer error_count;
    integer total_tests;

    greater_than_2bit dut (a, b, agb);

    initial begin
        $dumpfile("waves/greater_than_2bit.vcd"); 
        $dumpvars(0, greater_than_2bit_tb);
        $display("--- Starting Test (16 combinations) ---");
        error_count = 0;
        total_tests = 0;

        for (i=0; i<4; i=i+1) begin
            for(j=0; j<4; j=j+1) begin
                a = i[1:0]; b = j[1:0];
                expected_agb = (a > b);
                #10;
                total_tests = total_tests + 1;
                if (agb !== expected_agb) begin
                    $display("ERROR at %0t! a=%0d, b=%0d | Expected: %b, Got: %b", $time, a, b , expected_agb, agb);
                    error_count = error_count + 1;
                end else begin
                    $display("PASS: a=%0d, b=%0d | agb=%b", a, b, agb);
                end
            end
        end

        $display("\n========================================");
        $display("TEST SUMMARY:");
        $display("Total Combinations Tested: %0d", total_tests);
        
        if (error_count == 0) begin
            $display("RESULT: PERFECT PASS! (0 Errors)");
        end else begin
            $display("RESULT: FAILED! (%0d Errors found)", error_count);
        end
        $display("========================================\n");
        
        $finish;
    end
endmodule

ch01/waves/greater_than_2bit.vcd
$date
	Wed Mar 25 18:24:15 2026
$end
$version
	Icarus Verilog
$end
$timescale
	1ps
$end
$scope module greater_than_2bit_tb $end
$var wire 1 ! agb $end
$var reg 2 " a [1:0] $end
$var reg 2 # b [1:0] $end
$var reg 1 $ expected_agb $end
$var integer 32 % error_count [31:0] $end
$var integer 32 & i [31:0] $end
$var integer 32 ' j [31:0] $end
$var integer 32 ( total_tests [31:0] $end
$scope module dut $end
$var wire 2 ) a [1:0] $end
$var wire 1 ! agb $end
$var wire 2 * b [1:0] $end
$upscope $end
$upscope $end
$enddefinitions $end
$comment Show the parameter values. $end
$dumpall
$end
#0
$dumpvars
b0 *
b0 )
b0 (
b0 '
b0 &
b0 %
0$
b0 #
b0 "
0!
$end
#10000
b1 #
b1 *
b1 '
b1 (
#20000
b10 #
b10 *
b10 '
b10 (
#30000
b11 #
b11 *
b11 '
b11 (
#40000
1!
1$
b0 #
b0 *
b1 "
b1 )
b1 &
b0 '
b100 (
#50000
0!
0$
b1 #
b1 *
b1 '
b101 (
#60000
b10 #
b10 *
b10 '
b110 (
#70000
b11 #
b11 *
b11 '
b111 (
#80000
1!
1$
b0 #
b0 *
b10 "
b10 )
b10 &
b0 '
b1000 (
#90000
b1 #
b1 *
b1 '
b1001 (
#100000
0!
0$
b10 #
b10 *
b10 '
b1010 (
#110000
b11 #
b11 *
b11 '
b1011 (
#120000
1!
1$
b0 #
b0 *
b11 "
b11 )
b11 &
b0 '
b1100 (
#130000
b1 #
b1 *
b1 '
b1101 (
#140000
b10 #
b10 *
b10 '
b1110 (
#150000
0!
0$
b11 #
b11 *
b11 '
b1111 (
#160000
b100 &
b100 '
b10000 (
