ch03/rtl/barrel_shifter.v
module barrel_shifter #(
    parameter N = 8
) (
    input lr,
    input [$clog2(N) - 1 : 0] amt,
    input [N-1 : 0] data,
    output [N-1:0] shifted_data
);

    function [N-1:0] reverse(input [N-1:0] in);
        integer i;
        begin
            for (i=0; i<N; i=i+1) begin
                reverse[i] = in[N-1-i];
            end
        end
    endfunction


    wire [N-1:0] is_rev =  lr ? reverse(data) : data;
    wire [N-1:0] shifted = (is_rev >> amt) | (is_rev << (N - amt));
    assign shifted_data = lr ? reverse(shifted) : shifted;
    
endmodule

ch03/tb/barrel_shifter_tb.v
module barrel_shifter_tb (
);
    
    localparam N = 8;

    reg [N-1:0] data;
    reg [$clog2(N) - 1:0] amt;
    reg lr;
    wire [N-1:0] shifted_data;

    reg[N-1:0] expected;
    integer i, j;
    integer errors;

    barrel_shifter #(.N(N)) dut (lr, amt, data, shifted_data);

    initial begin
        
        // Dump so I can get the signals
        $dumpfile("waves/barrel_shifter.vcd");
        $dumpvars(0, barrel_shifter_tb);

        // Initialize 
        data = 8'b10110001;
        errors = 0;
        
        //Start test
        $display("--- Statrting Test  (N=%0d) ---", N);
        $display("Input data: %b", data);
        
        for (i=0; i<2; i=i+1) begin //Loop for lr
            lr = i;

            for (j=0; j<N; j=j+1) begin // Loop for amt (Check all shifting amounts)
                amt = j;
                // Calculate expected values
                if (lr == 0) expected = (data >> amt) | (data << (N-amt)); // Right shit
                else expected = (data << amt) | (data >> (N-amt)); // Left shift

                #10;

                // Check Values after giving time for logic to change
                if (shifted_data !== expected) begin
                    $display("ERROR: lr=%b, amt=%0d, data=%b | Expected: %b, Got: %b", lr, amt, data, expected, shifted_data);
                    errors = errors + 1;
                end else begin
                    $display("PASS: lr=%b, amt=%0d, data=%b | shifted_data=%b", lr, amt, data, shifted_data);
                end
            end 

        end

        // Summary of test results:
        $display("********************************");
        if (errors == 0) $display("RESULT: Test PASS (0 Errors)");
        else $display("RESULT: Test FAIL (%0d Errors)", errors);
        $display("********************************");

        $finish;

    end

endmodule

ch03/waves/barrel_shifter.vcd
$date
	Thu Mar 26 13:06:55 2026
$end
$version
	Icarus Verilog
$end
$timescale
	1s
$end
$scope module barrel_shifter_tb $end
$var wire 8 ! shifted_data [7:0] $end
$var parameter 32 " N $end
$var reg 3 # amt [2:0] $end
$var reg 8 $ data [7:0] $end
$var reg 8 % expected [7:0] $end
$var reg 1 & lr $end
$var integer 32 ' errors [31:0] $end
$var integer 32 ( i [31:0] $end
$var integer 32 ) j [31:0] $end
$scope module dut $end
$var wire 3 * amt [2:0] $end
$var wire 8 + data [7:0] $end
$var wire 1 & lr $end
$var wire 8 , shifted [7:0] $end
$var wire 8 - shifted_data [7:0] $end
$var wire 8 . is_rev [7:0] $end
$var parameter 32 / N $end
$scope function reverse $end
$var reg 8 0 in [7:0] $end
$var integer 32 1 i [31:0] $end
$upscope $end
$upscope $end
$upscope $end
$enddefinitions $end
$comment Show the parameter values. $end
$dumpall
b1000 /
b1000 "
$end
#0
$dumpvars
b1000 1
b10110001 0
b10110001 .
b10110001 -
b10110001 ,
b10110001 +
b0 *
b0 )
b0 (
b0 '
0&
b10110001 %
b10110001 $
b0 #
b10110001 !
$end
#10
b1000 1
b11011000 0
b11011000 !
b11011000 -
b11011000 ,
b11011000 %
b1 #
b1 *
b1 )
#20
b1000 1
b1101100 0
b1101100 !
b1101100 -
b1101100 ,
b1101100 %
b10 #
b10 *
b10 )
#30
b1000 1
b110110 0
b110110 !
b110110 -
b110110 ,
b110110 %
b11 #
b11 *
b11 )
#40
b1000 1
b11011 0
b11011 !
b11011 -
b11011 ,
b11011 %
b100 #
b100 *
b100 )
#50
b1000 1
b10001101 0
b10001101 !
b10001101 -
b10001101 ,
b10001101 %
b101 #
b101 *
b101 )
#60
b1000 1
b11000110 0
b11000110 !
b11000110 -
b11000110 ,
b11000110 %
b110 #
b110 *
b110 )
#70
b1000 1
b1100011 0
b1100011 !
b1100011 -
b1100011 ,
b1100011 %
b111 #
b111 *
b111 )
#80
b1000 1
b10001101 0
b10001101 ,
b10001101 .
b10110001 !
b10110001 -
b10110001 %
b0 #
b0 *
1&
b1 (
b0 )
#90
b1100011 !
b1100011 -
b1000 1
b11000110 0
b11000110 ,
b1100011 %
b1 #
b1 *
b1 )
#100
b11000110 !
b11000110 -
b1000 1
b1100011 0
b1100011 ,
b11000110 %
b10 #
b10 *
b10 )
#110
b10001101 !
b10001101 -
b1000 1
b10110001 0
b10110001 ,
b10001101 %
b11 #
b11 *
b11 )
#120
b11011 !
b11011 -
b1000 1
b11011000 0
b11011000 ,
b11011 %
b100 #
b100 *
b100 )
#130
b110110 !
b110110 -
b1000 1
b1101100 0
b1101100 ,
b110110 %
b101 #
b101 *
b101 )
#140
b1101100 !
b1101100 -
b1000 1
b110110 0
b110110 ,
b1101100 %
b110 #
b110 *
b110 )
#150
b11011000 !
b11011000 -
b1000 1
b11011 0
b11011 ,
b11011000 %
b111 #
b111 *
b111 )
#160
b10 (
b1000 )
