ch03/rtl/bcd_incrementor.v
module bcd_incrementor (
    input [11:0] num_in,
    output [11:0] bcd,
    output overflow
);
    
    wire en1, en2;

    bcd_inc_4bit uut0 (1'b1, num_in[3:0], bcd[3:0], en1);
    bcd_inc_4bit uut1 (en1, num_in[7:4], bcd[7:4], en2);
    bcd_inc_4bit uut2 (en2, num_in[11:8], bcd[11:8], overflow);


endmodule

module bcd_inc_4bit (
    input en,
    input [3:0] num,
    output reg [3:0] num_inc,
    output en_next
);
    always @(*) begin
        if (en) begin
            if (num == 4'd9) num_inc = 4'd0;
            else num_inc = num + 1;
        end else num_inc = num;
    end
    assign en_next = (en && num == 4'd9);
endmodule

ch03/tb/bcd_incrementor_tb.v
module bcd_incrementor_tb ();
    reg [11:0] num_in;
    wire [11:0] bcd;
    wire overflow;

    bcd_incrementor dut (num_in, bcd, overflow);

    integer i, j, k;
    reg [11:0] exp_bcd;
    reg exp_overflow;
    integer errors;

    initial begin
        $dumpfile("waves/bcd_incrementor.vcd");
        $dumpvars(0, bcd_incrementor_tb);

        errors = 0;

        $display("--- Starting Test ---");

        for(i=0; i<10; i=i+1) begin
            for(j=0; j<10; j=j+1) begin
                for(k=0; k<10; k=k+1) begin
                    num_in = {i[3:0], j[3:0], k[3:0]};

                    // GOLDEN MODEL
                    if (k == 9) begin
                        if (j == 9) begin
                            if (i == 9) begin
                                exp_bcd = 12'd0;
                                exp_overflow = 1'b1;
                            end else begin
                                exp_bcd = {(i[3:0] + 4'd1), 4'h0, 4'h0}; 
                                exp_overflow = 1'b0;
                            end
                        end else begin
                            exp_bcd = {i[3:0], (j[3:0] + 4'd1), 4'h0}; 
                            exp_overflow = 1'b0;
                        end
                    end else begin
                        exp_bcd = {i[3:0], j[3:0], (k[3:0] + 4'd1)}; 
                        exp_overflow = 1'b0;
                    end

                    #10; // Let combinational logic update
                    
                    // VERIFICATION
                    if (bcd !== exp_bcd || overflow !== exp_overflow) begin
                        $display("ERROR: num_in=%x| exp_bcd=%x, exp_overflow=%b | GOT: bcd=%x, overflow=%b", 
                                  num_in, exp_bcd, exp_overflow, bcd, overflow);
                        errors = errors + 1;
                    end 
                end
            end
        end

        // Test summary
        $display("========================================");
        if (errors == 0) $display("TEST PASS");
        else $display("TEST FAIL (%0d Errors)", errors);
        $display("========================================");

        $stop;

    end

endmodule

ch03/waves/bcd_incrementor.vcd
$date
	Thu Mar 26 15:45:17 2026
$end
$version
	Icarus Verilog
$end
$timescale
	1s
$end
$scope module bcd_incrementor_tb $end
$var wire 1 ! overflow $end
$var wire 12 " bcd [11:0] $end
$var reg 12 # exp_bcd [11:0] $end
$var reg 1 $ exp_overflow $end
$var reg 12 % num_in [11:0] $end
$var integer 32 & errors [31:0] $end
$var integer 32 ' i [31:0] $end
$var integer 32 ( j [31:0] $end
$var integer 32 ) k [31:0] $end
$scope module dut $end
$var wire 12 * num_in [11:0] $end
$var wire 1 ! overflow $end
$var wire 1 + en2 $end
$var wire 1 , en1 $end
$var wire 12 - bcd [11:0] $end
$scope module uut0 $end
$var wire 1 . en $end
$var wire 1 , en_next $end
$var wire 4 / num [3:0] $end
$var reg 4 0 num_inc [3:0] $end
$upscope $end
$scope module uut1 $end
$var wire 1 , en $end
$var wire 1 + en_next $end
$var wire 4 1 num [3:0] $end
$var reg 4 2 num_inc [3:0] $end
$upscope $end
$scope module uut2 $end
$var wire 1 + en $end
$var wire 1 ! en_next $end
$var wire 4 3 num [3:0] $end
$var reg 4 4 num_inc [3:0] $end
$upscope $end
$upscope $end
$upscope $end
$enddefinitions $end
$comment Show the parameter values. $end
$dumpall
$end
#0
$dumpvars
b0 4
b0 3
b0 2
b0 1
b1 0
b0 /
1.
b1 -
0,
0+
b0 *
b0 )
b0 (
b0 '
b0 &
b0 %
0$
b1 #
b1 "
0!
$end
#10
b10 "
b10 -
b10 0
b1 /
b10 #
b1 %
b1 *
b1 )
#20
b11 "
b11 -
b11 0
b10 /
b11 #
b10 %
b10 *
b10 )
#30
b100 "
b100 -
b100 0
b11 /
b100 #
b11 %
b11 *
b11 )
#40
b101 "
b101 -
b101 0
b100 /
b101 #
b100 %
b100 *
b100 )
#50
b110 "
b110 -
b110 0
b101 /
b110 #
b101 %
b101 *
b101 )
#60
b111 "
b111 -
b111 0
b110 /
b111 #
b110 %
b110 *
b110 )
#70
b1000 "
b1000 -
b1000 0
b111 /
b1000 #
b111 %
b111 *
b111 )
#80
b1001 "
b1001 -
b1001 0
b1000 /
b1001 #
b1000 %
b1000 *
b1000 )
#90
b10000 "
b10000 -
b1 2
b0 0
1,
b1001 /
b10000 #
b1001 %
b1001 *
b1001 )
#100
b10001 "
b10001 -
b1 0
0,
b1 2
b0 /
b1 1
b10001 #
b10000 %
b10000 *
b1 (
b0 )
#110
b10010 "
b10010 -
b10 0
b1 /
b10010 #
b10001 %
b10001 *
b1 )
#120
b10011 "
b10011 -
b11 0
b10 /
b10011 #
b10010 %
b10010 *
b10 )
#130
b10100 "
b10100 -
b100 0
b11 /
b10100 #
b10011 %
b10011 *
b11 )
#140
b10101 "
b10101 -
b101 0
b100 /
b10101 #
b10100 %
b10100 *
b100 )
#150
b10110 "
b10110 -
b110 0
b101 /
b10110 #
b10101 %
b10101 *
b101 )
#160
b10111 "
b10111 -
b111 0
b110 /
b10111 #
b10110 %
b10110 *
b110 )
#170
b11000 "
b11000 -
b1000 0
b111 /
b11000 #
b10111 %
b10111 *
b111 )
#180
b11001 "
b11001 -
b1001 0
b1000 /
b11001 #
b11000 %
b11000 *
b1000 )
#190
b100000 "
b100000 -
b10 2
b0 0
1,
b1001 /
b100000 #
b11001 %
b11001 *
b1001 )
#200
b100001 "
b100001 -
b1 0
0,
b10 2
b0 /
b10 1
b100001 #
b100000 %
b100000 *
b10 (
b0 )
#210
b100010 "
b100010 -
b10 0
b1 /
b100010 #
b100001 %
b100001 *
b1 )
#220
b100011 "
b100011 -
b11 0
b10 /
b100011 #
b100010 %
b100010 *
b10 )
#230
b100100 "
b100100 -
b100 0
b11 /
b100100 #
b100011 %
b100011 *
b11 )
#240
b100101 "
b100101 -
b101 0
b100 /
b100101 #
b100100 %
b100100 *
b100 )
#250
b100110 "
b100110 -
b110 0
b101 /
b100110 #
b100101 %
b100101 *
b101 )
#260
b100111 "
b100111 -
b111 0
b110 /
b100111 #
b100110 %
b100110 *
b110 )
#270
b101000 "
b101000 -
b1000 0
b111 /
b101000 #
b100111 %
b100111 *
b111 )
#280
b101001 "
b101001 -
b1001 0
b1000 /
b101001 #
b101000 %
b101000 *
b1000 )
#290
b110000 "
b110000 -
b11 2
b0 0
1,
b1001 /
b110000 #
b101001 %
b101001 *
b1001 )
#300
b110001 "
b110001 -
b1 0
0,
b11 2
b0 /
b11 1
b110001 #
b110000 %
b110000 *
b11 (
b0 )
#310
b110010 "
b110010 -
b10 0
b1 /
b110010 #
b110001 %
b110001 *
b1 )
#320
b110011 "
b110011 -
b11 0
b10 /
b110011 #
b110010 %
b110010 *
b10 )
#330
b110100 "
b110100 -
b100 0
b11 /
b110100 #
b110011 %
b110011 *
b11 )
#340
b110101 "
b110101 -
b101 0
b100 /
b110101 #
b110100 %
b110100 *
b100 )
#350
b110110 "
b110110 -
b110 0
b101 /
b110110 #
b110101 %
b110101 *
b101 )
#360
b110111 "
b110111 -
b111 0
b110 /
b110111 #
b110110 %
b110110 *
b110 )
#370
b111000 "
b111000 -
b1000 0
b111 /
b111000 #
b110111 %
b110111 *
b111 )
#380
b111001 "
b111001 -
b1001 0
b1000 /
b111001 #
b111000 %
b111000 *
b1000 )
#390
b1000000 "
b1000000 -
b100 2
b0 0
1,
b1001 /
b1000000 #
b111001 %
b111001 *
b1001 )
#400
b1000001 "
b1000001 -
b1 0
0,
b100 2
b0 /
b100 1
b1000001 #
b1000000 %
b1000000 *
b100 (
b0 )
#410
b1000010 "
b1000010 -
b10 0
b1 /
b1000010 #
b1000001 %
b1000001 *
b1 )
#420
b1000011 "
b1000011 -
b11 0
b10 /
b1000011 #
b1000010 %
b1000010 *
b10 )
#430
b1000100 "
b1000100 -
b100 0
b11 /
b1000100 #
b1000011 %
b1000011 *
b11 )
#440
b1000101 "
b1000101 -
b101 0
b100 /
b1000101 #
b1000100 %
b1000100 *
b100 )
#450
b1000110 "
b1000110 -
b110 0
b101 /
b1000110 #
b1000101 %
b1000101 *
b101 )
#460
b1000111 "
b1000111 -
b111 0
b110 /
b1000111 #
b1000110 %
b1000110 *
b110 )
#470
b1001000 "
b1001000 -
b1000 0
b111 /
b1001000 #
b1000111 %
b1000111 *
b111 )
#480
b1001001 "
b1001001 -
b1001 0
b1000 /
b1001001 #
b1001000 %
b1001000 *
b1000 )
#490
b1010000 "
b1010000 -
b101 2
b0 0
1,
b1001 /
b1010000 #
b1001001 %
b1001001 *
b1001 )
#500
b1010001 "
b1010001 -
b1 0
0,
b101 2
b0 /
b101 1
b1010001 #
b1010000 %
b1010000 *
b101 (
b0 )
#510
b1010010 "
b1010010 -
b10 0
b1 /
b1010010 #
b1010001 %
b1010001 *
b1 )
#520
b1010011 "
b1010011 -
b11 0
b10 /
b1010011 #
b1010010 %
b1010010 *
b10 )
#530
b1010100 "
b1010100 -
b100 0
b11 /
b1010100 #
b1010011 %
b1010011 *
b11 )
#540
b1010101 "
b1010101 -
b101 0
b100 /
b1010101 #
b1010100 %
b1010100 *
b100 )
#550
b1010110 "
b1010110 -
b110 0
b101 /
b1010110 #
b1010101 %
b1010101 *
b101 )
#560
b1010111 "
b1010111 -
b111 0
b110 /
b1010111 #
b1010110 %
b1010110 *
b110 )
#570
b1011000 "
b1011000 -
b1000 0
b111 /
b1011000 #
b1010111 %
b1010111 *
b111 )
#580
b1011001 "
b1011001 -
b1001 0
b1000 /
b1011001 #
b1011000 %
b1011000 *
b1000 )
#590
b1100000 "
b1100000 -
b110 2
b0 0
1,
b1001 /
b1100000 #
b1011001 %
b1011001 *
b1001 )
#600
b1100001 "
b1100001 -
b1 0
0,
b110 2
b0 /
b110 1
b1100001 #
b1100000 %
b1100000 *
b110 (
b0 )
#610
b1100010 "
b1100010 -
b10 0
b1 /
b1100010 #
b1100001 %
b1100001 *
b1 )
#620
b1100011 "
b1100011 -
b11 0
b10 /
b1100011 #
b1100010 %
b1100010 *
b10 )
#630
b1100100 "
b1100100 -
b100 0
b11 /
b1100100 #
b1100011 %
b1100011 *
b11 )
#640
b1100101 "
b1100101 -
b101 0
b100 /
b1100101 #
b1100100 %
b1100100 *
b100 )
#650
b1100110 "
b1100110 -
b110 0
b101 /
b1100110 #
b1100101 %
b1100101 *
b101 )
#660
b1100111 "
b1100111 -
b111 0
b110 /
b1100111 #
b1100110 %
b1100110 *
b110 )
#670
b1101000 "
b1101000 -
b1000 0
b111 /
b1101000 #
b1100111 %
b1100111 *
b111 )
#680
b1101001 "
b1101001 -
b1001 0
b1000 /
b1101001 #
b1101000 %
b1101000 *
b1000 )
#690
b1110000 "
b1110000 -
b111 2
b0 0
1,
b1001 /
b1110000 #
b1101001 %
b1101001 *
b1001 )
#700
b1110001 "
b1110001 -
b1 0
0,
b111 2
b0 /
b111 1
b1110001 #
b1110000 %
b1110000 *
b111 (
b0 )
#710
b1110010 "
b1110010 -
b10 0
b1 /
b1110010 #
b1110001 %
b1110001 *
b1 )
#720
b1110011 "
b1110011 -
b11 0
b10 /
b1110011 #
b1110010 %
b1110010 *
b10 )
#730
b1110100 "
b1110100 -
b100 0
b11 /
b1110100 #
b1110011 %
b1110011 *
b11 )
#740
b1110101 "
b1110101 -
b101 0
b100 /
b1110101 #
b1110100 %
b1110100 *
b100 )
#750
b1110110 "
b1110110 -
b110 0
b101 /
b1110110 #
b1110101 %
b1110101 *
b101 )
#760
b1110111 "
b1110111 -
b111 0
b110 /
b1110111 #
b1110110 %
b1110110 *
b110 )
#770
b1111000 "
b1111000 -
b1000 0
b111 /
b1111000 #
b1110111 %
b1110111 *
b111 )
#780
b1111001 "
b1111001 -
b1001 0
b1000 /
b1111001 #
b1111000 %
b1111000 *
b1000 )
#790
b10000000 "
b10000000 -
b1000 2
b0 0
1,
b1001 /
b10000000 #
b1111001 %
b1111001 *
b1001 )
#800
b10000001 "
b10000001 -
b1 0
0,
b1000 2
b0 /
b1000 1
b10000001 #
b10000000 %
b10000000 *
b1000 (
b0 )
#810
b10000010 "
b10000010 -
b10 0
b1 /
b10000010 #
b10000001 %
b10000001 *
b1 )
#820
b10000011 "
b10000011 -
b11 0
b10 /
b10000011 #
b10000010 %
b10000010 *
b10 )
#830
b10000100 "
b10000100 -
b100 0
b11 /
b10000100 #
b10000011 %
b10000011 *
b11 )
#840
b10000101 "
b10000101 -
b101 0
b100 /
b10000101 #
b10000100 %
b10000100 *
b100 )
#850
b10000110 "
b10000110 -
b110 0
b101 /
b10000110 #
b10000101 %
b10000101 *
b101 )
#860
b10000111 "
b10000111 -
b111 0
b110 /
b10000111 #
b10000110 %
b10000110 *
b110 )
#870
b10001000 "
b10001000 -
b1000 0
b111 /
b10001000 #
b10000111 %
b10000111 *
b111 )
#880
b10001001 "
b10001001 -
b1001 0
b1000 /
b10001001 #
b10001000 %
b10001000 *
b1000 )
#890
b10010000 "
b10010000 -
b1001 2
b0 0
1,
b1001 /
b10010000 #
b10001001 %
b10001001 *
b1001 )
#900
b10010001 "
b10010001 -
b0 4
b1 0
0,
b1001 2
0+
b0 /
b1001 1
b10010001 #
b10010000 %
b10010000 *
b1001 (
b0 )
#910
b10010010 "
b10010010 -
b10 0
b1 /
b10010010 #
b10010001 %
b10010001 *
b1 )
#920
b10010011 "
b10010011 -
b11 0
b10 /
b10010011 #
b10010010 %
b10010010 *
b10 )
#930
b10010100 "
b10010100 -
b100 0
b11 /
b10010100 #
b10010011 %
b10010011 *
b11 )
#940
b10010101 "
b10010101 -
b101 0
b100 /
b10010101 #
b10010100 %
b10010100 *
b100 )
#950
b10010110 "
b10010110 -
b110 0
b101 /
b10010110 #
b10010101 %
b10010101 *
b101 )
#960
b10010111 "
b10010111 -
b111 0
b110 /
b10010111 #
b10010110 %
b10010110 *
b110 )
#970
b10011000 "
b10011000 -
b1000 0
b111 /
b10011000 #
b10010111 %
b10010111 *
b111 )
#980
b10011001 "
b10011001 -
b1001 0
b1000 /
b10011001 #
b10011000 %
b10011000 *
b1000 )
#990
b1 4
b100000000 "
b100000000 -
1+
b0 2
b0 0
1,
b1001 /
b100000000 #
b10011001 %
b10011001 *
b1001 )
#1000
b100000001 "
b100000001 -
b1 0
0,
b0 2
0+
b1 4
b0 /
b0 1
b1 3
b100000001 #
b100000000 %
b100000000 *
b1 '
b0 (
b0 )
#1010
b100000010 "
b100000010 -
b10 0
b1 /
b100000010 #
b100000001 %
b100000001 *
b1 )
#1020
b100000011 "
b100000011 -
b11 0
b10 /
b100000011 #
b100000010 %
b100000010 *
b10 )
#1030
b100000100 "
b100000100 -
b100 0
b11 /
b100000100 #
b100000011 %
b100000011 *
b11 )
#1040
b100000101 "
b100000101 -
b101 0
b100 /
b100000101 #
b100000100 %
b100000100 *
b100 )
#1050
b100000110 "
b100000110 -
b110 0
b101 /
b100000110 #
b100000101 %
b100000101 *
b101 )
#1060
b100000111 "
b100000111 -
b111 0
b110 /
b100000111 #
b100000110 %
b100000110 *
b110 )
#1070
b100001000 "
b100001000 -
b1000 0
b111 /
b100001000 #
b100000111 %
b100000111 *
b111 )
#1080
b100001001 "
b100001001 -
b1001 0
b1000 /
b100001001 #
b100001000 %
b100001000 *
b1000 )
#1090
b100010000 "
b100010000 -
b1 2
b0 0
1,
b1001 /
b100010000 #
b100001001 %
b100001001 *
b1001 )
#1100
b100010001 "
b100010001 -
b1 0
0,
b1 2
b0 /
b1 1
b100010001 #
b100010000 %
b100010000 *
b1 (
b0 )
#1110
b100010010 "
b100010010 -
b10 0
b1 /
b100010010 #
b100010001 %
b100010001 *
b1 )
#1120
b100010011 "
b100010011 -
b11 0
b10 /
b100010011 #
b100010010 %
b100010010 *
b10 )
#1130
b100010100 "
b100010100 -
b100 0
b11 /
b100010100 #
b100010011 %
b100010011 *
b11 )
#1140
b100010101 "
b100010101 -
b101 0
b100 /
b100010101 #
b100010100 %
b100010100 *
b100 )
#1150
b100010110 "
b100010110 -
b110 0
b101 /
b100010110 #
b100010101 %
b100010101 *
b101 )
#1160
b100010111 "
b100010111 -
b111 0
b110 /
b100010111 #
b100010110 %
b100010110 *
b110 )
#1170
b100011000 "
b100011000 -
b1000 0
b111 /
b100011000 #
b100010111 %
b100010111 *
b111 )
#1180
b100011001 "
b100011001 -
b1001 0
b1000 /
b100011001 #
b100011000 %
b100011000 *
b1000 )
#1190
b100100000 "
b100100000 -
b10 2
b0 0
1,
b1001 /
b100100000 #
b100011001 %
b100011001 *
b1001 )
#1200
b100100001 "
b100100001 -
b1 0
0,
b10 2
b0 /
b10 1
b100100001 #
b100100000 %
b100100000 *
b10 (
b0 )
#1210
b100100010 "
b100100010 -
b10 0
b1 /
b100100010 #
b100100001 %
b100100001 *
b1 )
#1220
b100100011 "
b100100011 -
b11 0
b10 /
b100100011 #
b100100010 %
b100100010 *
b10 )
#1230
b100100100 "
b100100100 -
b100 0
b11 /
b100100100 #
b100100011 %
b100100011 *
b11 )
#1240
b100100101 "
b100100101 -
b101 0
b100 /
b100100101 #
b100100100 %
b100100100 *
b100 )
#1250
b100100110 "
b100100110 -
b110 0
b101 /
b100100110 #
b100100101 %
b100100101 *
b101 )
#1260
b100100111 "
b100100111 -
b111 0
b110 /
b100100111 #
b100100110 %
b100100110 *
b110 )
#1270
b100101000 "
b100101000 -
b1000 0
b111 /
b100101000 #
b100100111 %
b100100111 *
b111 )
#1280
b100101001 "
b100101001 -
b1001 0
b1000 /
b100101001 #
b100101000 %
b100101000 *
b1000 )
#1290
b100110000 "
b100110000 -
b11 2
b0 0
1,
b1001 /
b100110000 #
b100101001 %
b100101001 *
b1001 )
#1300
b100110001 "
b100110001 -
b1 0
0,
b11 2
b0 /
b11 1
b100110001 #
b100110000 %
b100110000 *
b11 (
b0 )
#1310
b100110010 "
b100110010 -
b10 0
b1 /
b100110010 #
b100110001 %
b100110001 *
b1 )
#1320
b100110011 "
b100110011 -
b11 0
b10 /
b100110011 #
b100110010 %
b100110010 *
b10 )
#1330
b100110100 "
b100110100 -
b100 0
b11 /
b100110100 #
b100110011 %
b100110011 *
b11 )
#1340
b100110101 "
b100110101 -
b101 0
b100 /
b100110101 #
b100110100 %
b100110100 *
b100 )
#1350
b100110110 "
b100110110 -
b110 0
b101 /
b100110110 #
b100110101 %
b100110101 *
b101 )
#1360
b100110111 "
b100110111 -
b111 0
b110 /
b100110111 #
b100110110 %
b100110110 *
b110 )
#1370
b100111000 "
b100111000 -
b1000 0
b111 /
b100111000 #
b100110111 %
b100110111 *
b111 )
#1380
b100111001 "
b100111001 -
b1001 0
b1000 /
b100111001 #
b100111000 %
b100111000 *
b1000 )
#1390
b101000000 "
b101000000 -
b100 2
b0 0
1,
b1001 /
b101000000 #
b100111001 %
b100111001 *
b1001 )
#1400
b101000001 "
b101000001 -
b1 0
0,
b100 2
b0 /
b100 1
b101000001 #
b101000000 %
b101000000 *
b100 (
b0 )
#1410
b101000010 "
b101000010 -
b10 0
b1 /
b101000010 #
b101000001 %
b101000001 *
b1 )
#1420
b101000011 "
b101000011 -
b11 0
b10 /
b101000011 #
b101000010 %
b101000010 *
b10 )
#1430
b101000100 "
b101000100 -
b100 0
b11 /
b101000100 #
b101000011 %
b101000011 *
b11 )
#1440
b101000101 "
b101000101 -
b101 0
b100 /
b101000101 #
b101000100 %
b101000100 *
b100 )
#1450
b101000110 "
b101000110 -
b110 0
b101 /
b101000110 #
b101000101 %
b101000101 *
b101 )
#1460
b101000111 "
b101000111 -
b111 0
b110 /
b101000111 #
b101000110 %
b101000110 *
b110 )
#1470
b101001000 "
b101001000 -
b1000 0
b111 /
b101001000 #
b101000111 %
b101000111 *
b111 )
#1480
b101001001 "
b101001001 -
b1001 0
b1000 /
b101001001 #
b101001000 %
b101001000 *
b1000 )
#1490
b101010000 "
b101010000 -
b101 2
b0 0
1,
b1001 /
b101010000 #
b101001001 %
b101001001 *
b1001 )
#1500
b101010001 "
b101010001 -
b1 0
0,
b101 2
b0 /
b101 1
b101010001 #
b101010000 %
b101010000 *
b101 (
b0 )
#1510
b101010010 "
b101010010 -
b10 0
b1 /
b101010010 #
b101010001 %
b101010001 *
b1 )
#1520
b101010011 "
b101010011 -
b11 0
b10 /
b101010011 #
b101010010 %
b101010010 *
b10 )
#1530
b101010100 "
b101010100 -
b100 0
b11 /
b101010100 #
b101010011 %
b101010011 *
b11 )
#1540
b101010101 "
b101010101 -
b101 0
b100 /
b101010101 #
b101010100 %
b101010100 *
b100 )
#1550
b101010110 "
b101010110 -
b110 0
b101 /
b101010110 #
b101010101 %
b101010101 *
b101 )
#1560
b101010111 "
b101010111 -
b111 0
b110 /
b101010111 #
b101010110 %
b101010110 *
b110 )
#1570
b101011000 "
b101011000 -
b1000 0
b111 /
b101011000 #
b101010111 %
b101010111 *
b111 )
#1580
b101011001 "
b101011001 -
b1001 0
b1000 /
b101011001 #
b101011000 %
b101011000 *
b1000 )
#1590
b101100000 "
b101100000 -
b110 2
b0 0
1,
b1001 /
b101100000 #
b101011001 %
b101011001 *
b1001 )
#1600
b101100001 "
b101100001 -
b1 0
0,
b110 2
b0 /
b110 1
b101100001 #
b101100000 %
b101100000 *
b110 (
b0 )
#1610
b101100010 "
b101100010 -
b10 0
b1 /
b101100010 #
b101100001 %
b101100001 *
b1 )
#1620
b101100011 "
b101100011 -
b11 0
b10 /
b101100011 #
b101100010 %
b101100010 *
b10 )
#1630
b101100100 "
b101100100 -
b100 0
b11 /
b101100100 #
b101100011 %
b101100011 *
b11 )
#1640
b101100101 "
b101100101 -
b101 0
b100 /
b101100101 #
b101100100 %
b101100100 *
b100 )
#1650
b101100110 "
b101100110 -
b110 0
b101 /
b101100110 #
b101100101 %
b101100101 *
b101 )
#1660
b101100111 "
b101100111 -
b111 0
b110 /
b101100111 #
b101100110 %
b101100110 *
b110 )
#1670
b101101000 "
b101101000 -
b1000 0
b111 /
b101101000 #
b101100111 %
b101100111 *
b111 )
#1680
b101101001 "
b101101001 -
b1001 0
b1000 /
b101101001 #
b101101000 %
b101101000 *
b1000 )
#1690
b101110000 "
b101110000 -
b111 2
b0 0
1,
b1001 /
b101110000 #
b101101001 %
b101101001 *
b1001 )
#1700
b101110001 "
b101110001 -
b1 0
0,
b111 2
b0 /
b111 1
b101110001 #
b101110000 %
b101110000 *
b111 (
b0 )
#1710
b101110010 "
b101110010 -
b10 0
b1 /
b101110010 #
b101110001 %
b101110001 *
b1 )
#1720
b101110011 "
b101110011 -
b11 0
b10 /
b101110011 #
b101110010 %
b101110010 *
b10 )
#1730
b101110100 "
b101110100 -
b100 0
b11 /
b101110100 #
b101110011 %
b101110011 *
b11 )
#1740
b101110101 "
b101110101 -
b101 0
b100 /
b101110101 #
b101110100 %
b101110100 *
b100 )
#1750
b101110110 "
b101110110 -
b110 0
b101 /
b101110110 #
b101110101 %
b101110101 *
b101 )
#1760
b101110111 "
b101110111 -
b111 0
b110 /
b101110111 #
b101110110 %
b101110110 *
b110 )
#1770
b101111000 "
b101111000 -
b1000 0
b111 /
b101111000 #
b101110111 %
b101110111 *
b111 )
#1780
b101111001 "
b101111001 -
b1001 0
b1000 /
b101111001 #
b101111000 %
b101111000 *
b1000 )
#1790
b110000000 "
b110000000 -
b1000 2
b0 0
1,
b1001 /
b110000000 #
b101111001 %
b101111001 *
b1001 )
#1800
b110000001 "
b110000001 -
b1 0
0,
b1000 2
b0 /
b1000 1
b110000001 #
b110000000 %
b110000000 *
b1000 (
b0 )
#1810
b110000010 "
b110000010 -
b10 0
b1 /
b110000010 #
b110000001 %
b110000001 *
b1 )
#1820
b110000011 "
b110000011 -
b11 0
b10 /
b110000011 #
b110000010 %
b110000010 *
b10 )
#1830
b110000100 "
b110000100 -
b100 0
b11 /
b110000100 #
b110000011 %
b110000011 *
b11 )
#1840
b110000101 "
b110000101 -
b101 0
b100 /
b110000101 #
b110000100 %
b110000100 *
b100 )
#1850
b110000110 "
b110000110 -
b110 0
b101 /
b110000110 #
b110000101 %
b110000101 *
b101 )
#1860
b110000111 "
b110000111 -
b111 0
b110 /
b110000111 #
b110000110 %
b110000110 *
b110 )
#1870
b110001000 "
b110001000 -
b1000 0
b111 /
b110001000 #
b110000111 %
b110000111 *
b111 )
#1880
b110001001 "
b110001001 -
b1001 0
b1000 /
b110001001 #
b110001000 %
b110001000 *
b1000 )
#1890
b110010000 "
b110010000 -
b1001 2
b0 0
1,
b1001 /
b110010000 #
b110001001 %
b110001001 *
b1001 )
#1900
b110010001 "
b110010001 -
b1 4
b1 0
0,
b1001 2
0+
b0 /
b1001 1
b110010001 #
b110010000 %
b110010000 *
b1001 (
b0 )
#1910
b110010010 "
b110010010 -
b10 0
b1 /
b110010010 #
b110010001 %
b110010001 *
b1 )
#1920
b110010011 "
b110010011 -
b11 0
b10 /
b110010011 #
b110010010 %
b110010010 *
b10 )
#1930
b110010100 "
b110010100 -
b100 0
b11 /
b110010100 #
b110010011 %
b110010011 *
b11 )
#1940
b110010101 "
b110010101 -
b101 0
b100 /
b110010101 #
b110010100 %
b110010100 *
b100 )
#1950
b110010110 "
b110010110 -
b110 0
b101 /
b110010110 #
b110010101 %
b110010101 *
b101 )
#1960
b110010111 "
b110010111 -
b111 0
b110 /
b110010111 #
b110010110 %
b110010110 *
b110 )
#1970
b110011000 "
b110011000 -
b1000 0
b111 /
b110011000 #
b110010111 %
b110010111 *
b111 )
#1980
b110011001 "
b110011001 -
b1001 0
b1000 /
b110011001 #
b110011000 %
b110011000 *
b1000 )
#1990
b10 4
b1000000000 "
b1000000000 -
1+
b0 2
b0 0
1,
b1001 /
b1000000000 #
b110011001 %
b110011001 *
b1001 )
#2000
b1000000001 "
b1000000001 -
b1 0
0,
b0 2
0+
b10 4
b0 /
b0 1
b10 3
b1000000001 #
b1000000000 %
b1000000000 *
b10 '
b0 (
b0 )
#2010
b1000000010 "
b1000000010 -
b10 0
b1 /
b1000000010 #
b1000000001 %
b1000000001 *
b1 )
#2020
b1000000011 "
b1000000011 -
b11 0
b10 /
b1000000011 #
b1000000010 %
b1000000010 *
b10 )
#2030
b1000000100 "
b1000000100 -
b100 0
b11 /
b1000000100 #
b1000000011 %
b1000000011 *
b11 )
#2040
b1000000101 "
b1000000101 -
b101 0
b100 /
b1000000101 #
b1000000100 %
b1000000100 *
b100 )
#2050
b1000000110 "
b1000000110 -
b110 0
b101 /
b1000000110 #
b1000000101 %
b1000000101 *
b101 )
#2060
b1000000111 "
b1000000111 -
b111 0
b110 /
b1000000111 #
b1000000110 %
b1000000110 *
b110 )
#2070
b1000001000 "
b1000001000 -
b1000 0
b111 /
b1000001000 #
b1000000111 %
b1000000111 *
b111 )
#2080
b1000001001 "
b1000001001 -
b1001 0
b1000 /
b1000001001 #
b1000001000 %
b1000001000 *
b1000 )
#2090
b1000010000 "
b1000010000 -
b1 2
b0 0
1,
b1001 /
b1000010000 #
b1000001001 %
b1000001001 *
b1001 )
#2100
b1000010001 "
b1000010001 -
b1 0
0,
b1 2
b0 /
b1 1
b1000010001 #
b1000010000 %
b1000010000 *
b1 (
b0 )
#2110
b1000010010 "
b1000010010 -
b10 0
b1 /
b1000010010 #
b1000010001 %
b1000010001 *
b1 )
#2120
b1000010011 "
b1000010011 -
b11 0
b10 /
b1000010011 #
b1000010010 %
b1000010010 *
b10 )
#2130
b1000010100 "
b1000010100 -
b100 0
b11 /
b1000010100 #
b1000010011 %
b1000010011 *
b11 )
#2140
b1000010101 "
b1000010101 -
b101 0
b100 /
b1000010101 #
b1000010100 %
b1000010100 *
b100 )
#2150
b1000010110 "
b1000010110 -
b110 0
b101 /
b1000010110 #
b1000010101 %
b1000010101 *
b101 )
#2160
b1000010111 "
b1000010111 -
b111 0
b110 /
b1000010111 #
b1000010110 %
b1000010110 *
b110 )
#2170
b1000011000 "
b1000011000 -
b1000 0
b111 /
b1000011000 #
b1000010111 %
b1000010111 *
b111 )
#2180
b1000011001 "
b1000011001 -
b1001 0
b1000 /
b1000011001 #
b1000011000 %
b1000011000 *
b1000 )
#2190
b1000100000 "
b1000100000 -
b10 2
b0 0
1,
b1001 /
b1000100000 #
b1000011001 %
b1000011001 *
b1001 )
#2200
b1000100001 "
b1000100001 -
b1 0
0,
b10 2
b0 /
b10 1
b1000100001 #
b1000100000 %
b1000100000 *
b10 (
b0 )
#2210
b1000100010 "
b1000100010 -
b10 0
b1 /
b1000100010 #
b1000100001 %
b1000100001 *
b1 )
#2220
b1000100011 "
b1000100011 -
b11 0
b10 /
b1000100011 #
b1000100010 %
b1000100010 *
b10 )
#2230
b1000100100 "
b1000100100 -
b100 0
b11 /
b1000100100 #
b1000100011 %
b1000100011 *
b11 )
#2240
b1000100101 "
b1000100101 -
b101 0
b100 /
b1000100101 #
b1000100100 %
b1000100100 *
b100 )
#2250
b1000100110 "
b1000100110 -
b110 0
b101 /
b1000100110 #
b1000100101 %
b1000100101 *
b101 )
#2260
b1000100111 "
b1000100111 -
b111 0
b110 /
b1000100111 #
b1000100110 %
b1000100110 *
b110 )
#2270
b1000101000 "
b1000101000 -
b1000 0
b111 /
b1000101000 #
b1000100111 %
b1000100111 *
b111 )
#2280
b1000101001 "
b1000101001 -
b1001 0
b1000 /
b1000101001 #
b1000101000 %
b1000101000 *
b1000 )
#2290
b1000110000 "
b1000110000 -
b11 2
b0 0
1,
b1001 /
b1000110000 #
b1000101001 %
b1000101001 *
b1001 )
