ch03/rtl/dual_priority_encoder.v
module dual_priority_encoder (
    input [11:0] req,
    output [$clog2(12)-1:0] first, second,
    output first_valid, second_valid
);
    // Find the first one index
    priority_encoder uut0 (req, first, first_valid);

    // Create a mask if valid
    wire [11:0] mask = first_valid ? (12'b1 << first) : 12'b0;

    // Remove the first one using the mask
    wire [11:0] dup_req = mask ^ req;

    // find second 1 index
    priority_encoder uut1 (dup_req, second, second_valid);
endmodule

module priority_encoder (
    input [11:0] data,
    output [$clog2(12) - 1:0] index,
    output valid
);

    wire [2:0] valids;
    wire [1:0] indexes [2:0];

    prio_422 uut0 (data[3:0], indexes[0], valids[0]);
    prio_422 uut1 (data[7:4], indexes[1], valids[1]);
    prio_422 uut2 (data[11:8], indexes[2], valids[2]);

    assign valid = |valids;
    assign index = (valids[2]) ? {2'd2, indexes[2]} : (valids[1]) ? {2'd1, indexes[1]} : (valids[0]) ? {2'd0, indexes[0]} : 4'd0; 



endmodule

module prio_422 (
    input[3:0] data,
    output [1:0] index,
    output valid
);

    assign valid = |data;
    assign index = (data[3]) ? 2'd3 :
                   (data[2]) ? 2'd2 :
                   (data[1]) ? 2'd1 : 2'd0;
endmodule

ch03/tb/dual_priority_encoder_tb.v
module dual_priority_encoder_tb (
);
    reg [11:0] req;
    wire [3:0] first, second;
    wire first_valid, second_valid;

    dual_priority_encoder dut (req, first, second, first_valid, second_valid);

    reg [3:0] exp_first, exp_second;
    reg exp_first_valid, exp_second_valid;

    integer i ,j;
    integer errors;
    integer first_found, second_found;

    initial begin
        
        // Dump so I can get the signals
        $dumpfile("waves/dual_priority_encoder.vcd");
        $dumpvars(0, dual_priority_encoder_tb);

        errors = 0;

        $display("--- Starting Test ---");

        // Loop through all possible combinations of req
        for (i=0; i<4096; i=i+1) begin
            req = i[11:0];
            exp_first = 0;
            exp_second = 0;
            exp_first_valid = 0;
            exp_second_valid = 0;
            first_found = 0;
            second_found = 0;

            // Golden model to verifiy
            for (j=11; j >= 0; j=j-1) begin
                if (req[j] == 1'b1) begin
                    if (first_found == 0) begin
                        exp_first = j;
                        exp_first_valid = 1'b1;
                        first_found = 1;
                    end else if (second_found == 0) begin
                        exp_second = j;
                        exp_second_valid = 1'b1;
                        second_found = 1;
                    end
                end
            end

            // Let logic updat
            #10;

            // Verification
            if ((first_valid !== exp_first_valid) ||
                (second_valid !== exp_second_valid) ||
                (exp_first_valid && (first !== exp_first)) ||
                (exp_second_valid && (second !== exp_second))) begin
                $display("ERROR: req=%b, Expected: valid_first=%b, first=%0d | valid_second=%b, second=%0d", req, exp_first_valid, exp_first, exp_second_valid, exp_second);
                $display("GOT:                     valid_first=%b, first=%0d | valid_second=%b, second=%0d", first_valid, first, second_valid, second);
                errors = errors + 1;
            end 
        end

        // Summary
        $display("*******************************");
        if (errors == 0) $display("RESULT PASS");
        else $display("RESULT FAIL: %0d Errors", errors);
        $display("*******************************");

        $finish;


    end

endmodule

ch03/waves/dual_priority_encoder.vcd
$date
	Thu Mar 26 14:47:49 2026
$end
$version
	Icarus Verilog
$end
$timescale
	1s
$end
$scope module dual_priority_encoder_tb $end
$var wire 1 ! second_valid $end
$var wire 4 " second [3:0] $end
$var wire 1 # first_valid $end
$var wire 4 $ first [3:0] $end
$var reg 4 % exp_first [3:0] $end
$var reg 1 & exp_first_valid $end
$var reg 4 ' exp_second [3:0] $end
$var reg 1 ( exp_second_valid $end
$var reg 12 ) req [11:0] $end
$var integer 32 * errors [31:0] $end
$var integer 32 + first_found [31:0] $end
$var integer 32 , i [31:0] $end
$var integer 32 - j [31:0] $end
$var integer 32 . second_found [31:0] $end
$scope module dut $end
$var wire 12 / dup_req [11:0] $end
$var wire 12 0 req [11:0] $end
$var wire 1 ! second_valid $end
$var wire 4 1 second [3:0] $end
$var wire 12 2 mask [11:0] $end
$var wire 1 # first_valid $end
$var wire 4 3 first [3:0] $end
$scope module uut0 $end
$var wire 12 4 data [11:0] $end
$var wire 3 5 valids [2:0] $end
$var wire 1 # valid $end
$var wire 4 6 index [3:0] $end
$scope module uut0 $end
$var wire 4 7 data [3:0] $end
$var wire 1 8 valid $end
$var wire 2 9 index [1:0] $end
$upscope $end
$scope module uut1 $end
$var wire 4 : data [3:0] $end
$var wire 1 ; valid $end
$var wire 2 < index [1:0] $end
$upscope $end
$scope module uut2 $end
$var wire 4 = data [3:0] $end
$var wire 1 > valid $end
$var wire 2 ? index [1:0] $end
$upscope $end
$upscope $end
$scope module uut1 $end
$var wire 12 @ data [11:0] $end
$var wire 3 A valids [2:0] $end
$var wire 1 ! valid $end
$var wire 4 B index [3:0] $end
$scope module uut0 $end
$var wire 4 C data [3:0] $end
$var wire 1 D valid $end
$var wire 2 E index [1:0] $end
$upscope $end
$scope module uut1 $end
$var wire 4 F data [3:0] $end
$var wire 1 G valid $end
$var wire 2 H index [1:0] $end
$upscope $end
$scope module uut2 $end
$var wire 4 I data [3:0] $end
$var wire 1 J valid $end
$var wire 2 K index [1:0] $end
$upscope $end
$upscope $end
$upscope $end
$upscope $end
$enddefinitions $end
$comment Show the parameter values. $end
$dumpall
$end
#0
$dumpvars
b0 K
0J
b0 I
b0 H
0G
b0 F
b0 E
0D
b0 C
b0 B
b0 A
b0 @
b0 ?
0>
b0 =
b0 <
0;
b0 :
b0 9
08
b0 7
b0 6
b0 5
b0 4
b0 3
b0 2
b0 1
b0 0
b0 /
b0 .
b11111111111111111111111111111111 -
b0 ,
b0 +
b0 *
b0 )
0(
b0 '
0&
b0 %
b0 $
0#
b0 "
0!
$end
#10
0!
b0 A
b1 2
0D
b0 C
1#
b1 5
b0 /
b0 @
18
b1 7
b1 +
1&
b11111111111111111111111111111111 -
b1 )
b1 0
b1 4
b1 ,
#20
b0 "
b0 1
b0 B
b10 2
b1 $
b1 3
b1 6
b0 E
b1 9
0!
b0 A
0D
b0 C
b0 /
b0 @
b10 7
b1 %
b11111111111111111111111111111111 -
b1 +
1&
b10 )
b10 0
b10 4
b10 ,
#30
1!
b1 A
1D
b1 C
b1 /
b1 @
b11 7
b1 .
1(
b11111111111111111111111111111111 -
b1 +
1&
b1 %
b11 )
b11 0
b11 4
b11 ,
#40
0!
b0 A
0D
b0 "
b0 1
b0 B
b100 2
b10 $
b10 3
b10 6
b0 E
b10 9
b0 C
b0 /
b0 @
b100 7
b11111111111111111111111111111111 -
b0 .
b1 +
0(
1&
b10 %
b100 )
b100 0
b100 4
b100 ,
#50
1!
b1 A
1D
b1 C
b1 /
b1 @
b101 7
b1 .
1(
b11111111111111111111111111111111 -
b1 +
1&
b10 %
b101 )
b101 0
b101 4
b101 ,
#60
b1 "
b1 1
b1 B
b1 E
b10 C
b10 /
b10 @
b110 7
b1 '
b11111111111111111111111111111111 -
b1 .
b1 +
1(
1&
b10 %
b110 )
b110 0
b110 4
b110 ,
#70
b11 C
b11 /
b11 @
b111 7
b11111111111111111111111111111111 -
b1 .
b1 +
1(
1&
b1 '
b10 %
b111 )
b111 0
b111 4
b111 ,
#80
0!
b0 A
0D
b0 "
b0 1
b0 B
b1000 2
b11 $
b11 3
b11 6
b0 E
b11 9
b0 C
b0 /
b0 @
b1000 7
b11111111111111111111111111111111 -
b0 .
b1 +
0(
1&
b0 '
b11 %
b1000 )
b1000 0
b1000 4
b1000 ,
#90
1!
b1 A
1D
b1 C
b1 /
b1 @
b1001 7
b1 .
1(
b11111111111111111111111111111111 -
b1 +
1&
b11 %
b1001 )
b1001 0
b1001 4
b1001 ,
#100
b1 "
b1 1
b1 B
b1 E
b10 C
b10 /
b10 @
b1010 7
b1 '
b11111111111111111111111111111111 -
b1 .
b1 +
1(
1&
b11 %
b1010 )
b1010 0
b1010 4
b1010 ,
#110
b11 C
b11 /
b11 @
b1011 7
b11111111111111111111111111111111 -
b1 .
b1 +
1(
1&
b1 '
b11 %
b1011 )
b1011 0
b1011 4
b1011 ,
#120
b10 "
b10 1
b10 B
b10 E
b100 C
b100 /
b100 @
b1100 7
b11111111111111111111111111111111 -
b1 .
b1 +
1(
1&
b10 '
b11 %
b1100 )
b1100 0
b1100 4
b1100 ,
#130
b101 C
b101 /
b101 @
b1101 7
b11111111111111111111111111111111 -
b1 .
b1 +
1(
1&
b10 '
b11 %
b1101 )
b1101 0
b1101 4
b1101 ,
#140
b110 C
b110 /
b110 @
b1110 7
b11111111111111111111111111111111 -
b1 .
b1 +
1(
1&
b10 '
b11 %
b1110 )
b1110 0
b1110 4
b1110 ,
#150
b111 C
b111 /
b111 @
b1111 7
b11111111111111111111111111111111 -
b1 .
b1 +
1(
1&
b10 '
b11 %
b1111 )
b1111 0
b1111 4
b1111 ,
#160
0!
0D
b0 "
b0 1
b0 B
b10000 2
b100 $
b100 3
b100 6
b0 E
b0 A
b0 9
b0 C
0G
b0 F
b10 5
b0 /
b0 @
08
b0 7
1;
b1 :
b11111111111111111111111111111111 -
b0 .
b1 +
0(
1&
b0 '
b100 %
b10000 )
b10000 0
b10000 4
b10000 ,
#170
1!
b1 A
1D
b1 C
b11 5
b1 /
b1 @
18
b1 7
b1 .
1(
b11111111111111111111111111111111 -
b1 +
1&
b100 %
b10001 )
b10001 0
b10001 4
b10001 ,
#180
b1 "
b1 1
b1 B
b1 E
b1 9
b10 C
b10 /
b10 @
b10 7
b1 '
b11111111111111111111111111111111 -
b1 .
b1 +
1(
1&
b100 %
b10010 )
b10010 0
b10010 4
b10010 ,
#190
b11 C
b11 /
b11 @
b11 7
b11111111111111111111111111111111 -
b1 .
b1 +
1(
1&
b1 '
b100 %
b10011 )
b10011 0
b10011 4
b10011 ,
#200
b10 "
b10 1
b10 B
b10 E
b10 9
b100 C
b100 /
b100 @
b100 7
b11111111111111111111111111111111 -
b1 .
b1 +
1(
1&
b10 '
b100 %
b10100 )
b10100 0
b10100 4
b10100 ,
#210
b101 C
b101 /
b101 @
b101 7
b11111111111111111111111111111111 -
b1 .
b1 +
1(
1&
b10 '
b100 %
b10101 )
b10101 0
b10101 4
b10101 ,
#220
b110 C
b110 /
b110 @
b110 7
b11111111111111111111111111111111 -
b1 .
b1 +
1(
1&
b10 '
b100 %
b10110 )
b10110 0
b10110 4
b10110 ,
#230
b111 C
b111 /
b111 @
b111 7
b11111111111111111111111111111111 -
b1 .
b1 +
1(
1&
b10 '
b100 %
b10111 )
b10111 0
b10111 4
b10111 ,
#240
b11 "
b11 1
b11 B
b11 E
b11 9
b1000 C
b1000 /
b1000 @
b1000 7
b11111111111111111111111111111111 -
b1 .
b1 +
1(
1&
b11 '
b100 %
b11000 )
b11000 0
b11000 4
b11000 ,
#250
b1001 C
b1001 /
b1001 @
b1001 7
b11111111111111111111111111111111 -
b1 .
b1 +
1(
1&
b11 '
b100 %
b11001 )
b11001 0
b11001 4
b11001 ,
#260
b1010 C
b1010 /
b1010 @
b1010 7
b11111111111111111111111111111111 -
b1 .
b1 +
1(
1&
b11 '
b100 %
b11010 )
b11010 0
b11010 4
b11010 ,
#270
b1011 C
b1011 /
b1011 @
b1011 7
b11111111111111111111111111111111 -
b1 .
b1 +
1(
1&
b11 '
b100 %
b11011 )
b11011 0
b11011 4
b11011 ,
#280
b1100 C
b1100 /
b1100 @
b1100 7
b11111111111111111111111111111111 -
b1 .
b1 +
1(
1&
b11 '
b100 %
b11100 )
b11100 0
b11100 4
b11100 ,
#290
b1101 C
b1101 /
b1101 @
b1101 7
b11111111111111111111111111111111 -
b1 .
b1 +
1(
1&
b11 '
b100 %
b11101 )
b11101 0
b11101 4
b11101 ,
#300
b1110 C
b1110 /
b1110 @
b1110 7
b11111111111111111111111111111111 -
b1 .
b1 +
1(
1&
b11 '
b100 %
b11110 )
b11110 0
b11110 4
b11110 ,
#310
b1111 C
b1111 /
b1111 @
b1111 7
b11111111111111111111111111111111 -
b1 .
b1 +
1(
1&
b11 '
b100 %
b11111 )
b11111 0
b11111 4
b11111 ,
#320
0!
b100000 2
b101 $
b101 3
b101 6
b0 "
b0 1
b0 B
b0 H
b1 <
b0 E
b0 A
b0 9
0D
b0 C
0G
b0 F
b10 5
b0 /
b0 @
08
b0 7
b10 :
b11111111111111111111111111111111 -
b0 .
b1 +
0(
1&
b0 '
b101 %
b100000 )
b100000 0
b100000 4
b100000 ,
#330
1!
b1 A
1D
b1 C
b11 5
b1 /
b1 @
18
b1 7
b1 .
1(
b11111111111111111111111111111111 -
b1 +
1&
b101 %
b100001 )
b100001 0
b100001 4
b100001 ,
#340
b1 "
b1 1
b1 B
b1 E
b1 9
b10 C
b10 /
b10 @
b10 7
b1 '
b11111111111111111111111111111111 -
b1 .
b1 +
1(
1&
b101 %
b100010 )
b100010 0
b100010 4
b100010 ,
#350
b11 C
b11 /
b11 @
b11 7
b11111111111111111111111111111111 -
b1 .
b1 +
1(
1&
b1 '
b101 %
b100011 )
b100011 0
b100011 4
b100011 ,
#360
b10 "
b10 1
b10 B
b10 E
b10 9
b100 C
b100 /
b100 @
b100 7
b11111111111111111111111111111111 -
b1 .
b1 +
1(
1&
b10 '
b101 %
b100100 )
b100100 0
b100100 4
b100100 ,
#370
b101 C
b101 /
b101 @
b101 7
b11111111111111111111111111111111 -
b1 .
b1 +
1(
1&
b10 '
b101 %
b100101 )
b100101 0
b100101 4
b100101 ,
#380
b110 C
b110 /
b110 @
b110 7
b11111111111111111111111111111111 -
b1 .
b1 +
1(
1&
b10 '
b101 %
b100110 )
b100110 0
b100110 4
b100110 ,
#390
b111 C
b111 /
b111 @
b111 7
b11111111111111111111111111111111 -
b1 .
b1 +
1(
1&
b10 '
b101 %
b100111 )
b100111 0
b100111 4
b100111 ,
#400
b11 "
b11 1
b11 B
b11 E
b11 9
b1000 C
b1000 /
b1000 @
b1000 7
b11111111111111111111111111111111 -
b1 .
b1 +
1(
1&
b11 '
b101 %
b101000 )
b101000 0
b101000 4
b101000 ,
#410
b1001 C
b1001 /
b1001 @
b1001 7
b11111111111111111111111111111111 -
b1 .
b1 +
1(
1&
b11 '
b101 %
b101001 )
b101001 0
b101001 4
b101001 ,
#420
b1010 C
b1010 /
b1010 @
b1010 7
b11111111111111111111111111111111 -
b1 .
b1 +
1(
1&
b11 '
b101 %
b101010 )
b101010 0
b101010 4
b101010 ,
#430
b1011 C
b1011 /
b1011 @
b1011 7
b11111111111111111111111111111111 -
b1 .
b1 +
1(
1&
b11 '
b101 %
b101011 )
b101011 0
b101011 4
b101011 ,
#440
b1100 C
b1100 /
b1100 @
b1100 7
b11111111111111111111111111111111 -
b1 .
b1 +
1(
1&
b11 '
b101 %
b101100 )
b101100 0
b101100 4
b101100 ,
#450
b1101 C
b1101 /
b1101 @
b1101 7
b11111111111111111111111111111111 -
b1 .
b1 +
1(
1&
b11 '
b101 %
b101101 )
b101101 0
b101101 4
b101101 ,
#460
b1110 C
b1110 /
b1110 @
b1110 7
b11111111111111111111111111111111 -
b1 .
b1 +
1(
1&
b11 '
b101 %
b101110 )
b101110 0
b101110 4
b101110 ,
#470
b1111 C
b1111 /
b1111 @
b1111 7
b11111111111111111111111111111111 -
b1 .
b1 +
1(
1&
b11 '
b101 %
b101111 )
b101111 0
b101111 4
b101111 ,
#480
b100 "
b100 1
b100 B
b0 E
b10 A
b0 9
0D
b0 C
1G
b1 F
b10 5
b10000 /
b10000 @
08
b0 7
b11 :
b11111111111111111111111111111111 -
b1 .
b1 +
1(
1&
b100 '
b101 %
b110000 )
b110000 0
b110000 4
b110000 ,
#490
b11 A
1D
b1 C
b11 5
b10001 /
b10001 @
18
b1 7
b11111111111111111111111111111111 -
b1 .
b1 +
1(
1&
b100 '
b101 %
b110001 )
b110001 0
b110001 4
b110001 ,
#500
b1 E
b1 9
b10 C
b10010 /
b10010 @
b10 7
b11111111111111111111111111111111 -
b1 .
b1 +
1(
1&
b100 '
b101 %
b110010 )
b110010 0
b110010 4
b110010 ,
#510
b11 C
b10011 /
b10011 @
b11 7
b11111111111111111111111111111111 -
b1 .
b1 +
1(
1&
b100 '
b101 %
b110011 )
b110011 0
b110011 4
b110011 ,
#520
b10 E
b10 9
b100 C
b10100 /
b10100 @
b100 7
b11111111111111111111111111111111 -
b1 .
b1 +
1(
1&
b100 '
b101 %
b110100 )
b110100 0
b110100 4
b110100 ,
#530
b101 C
b10101 /
b10101 @
b101 7
b11111111111111111111111111111111 -
b1 .
b1 +
1(
1&
b100 '
b101 %
b110101 )
b110101 0
b110101 4
b110101 ,
#540
b110 C
b10110 /
b10110 @
b110 7
b11111111111111111111111111111111 -
b1 .
b1 +
1(
1&
b100 '
b101 %
b110110 )
b110110 0
b110110 4
b110110 ,
#550
b111 C
b10111 /
b10111 @
b111 7
b11111111111111111111111111111111 -
b1 .
b1 +
1(
1&
b100 '
b101 %
b110111 )
b110111 0
b110111 4
b110111 ,
#560
b11 E
b11 9
b1000 C
b11000 /
b11000 @
b1000 7
b11111111111111111111111111111111 -
b1 .
b1 +
1(
1&
b100 '
b101 %
b111000 )
b111000 0
b111000 4
b111000 ,
#570
b1001 C
b11001 /
b11001 @
b1001 7
b11111111111111111111111111111111 -
b1 .
b1 +
1(
1&
b100 '
b101 %
b111001 )
b111001 0
b111001 4
b111001 ,
#580
b1010 C
b11010 /
b11010 @
b1010 7
b11111111111111111111111111111111 -
b1 .
b1 +
1(
1&
b100 '
b101 %
b111010 )
b111010 0
b111010 4
b111010 ,
#590
b1011 C
b11011 /
b11011 @
b1011 7
b11111111111111111111111111111111 -
b1 .
b1 +
1(
1&
b100 '
b101 %
b111011 )
b111011 0
b111011 4
b111011 ,
#600
b1100 C
b11100 /
b11100 @
b1100 7
b11111111111111111111111111111111 -
b1 .
b1 +
1(
1&
b100 '
b101 %
b111100 )
b111100 0
b111100 4
b111100 ,
#610
b1101 C
b11101 /
b11101 @
b1101 7
b11111111111111111111111111111111 -
b1 .
b1 +
1(
1&
b100 '
b101 %
b111101 )
b111101 0
b111101 4
b111101 ,
#620
b1110 C
b11110 /
b11110 @
b1110 7
b11111111111111111111111111111111 -
b1 .
b1 +
1(
1&
b100 '
b101 %
b111110 )
b111110 0
b111110 4
b111110 ,
#630
b1111 C
b11111 /
b11111 @
b1111 7
b11111111111111111111111111111111 -
b1 .
b1 +
1(
1&
b100 '
b101 %
b111111 )
b111111 0
b111111 4
b111111 ,
#640
0!
0G
b0 "
b0 1
b0 B
b1000000 2
b110 $
b110 3
b110 6
b0 H
b0 E
b10 <
b0 A
b0 9
0D
b0 C
b0 F
b10 5
b0 /
b0 @
08
b0 7
b100 :
b11111111111111111111111111111111 -
b0 .
b1 +
0(
1&
b0 '
b110 %
b1000000 )
b1000000 0
b1000000 4
b1000000 ,
#650
1!
b1 A
1D
b1 C
b11 5
b1 /
b1 @
18
b1 7
b1 .
1(
b11111111111111111111111111111111 -
b1 +
1&
b110 %
b1000001 )
b1000001 0
b1000001 4
b1000001 ,
#660
b1 "
b1 1
b1 B
b1 E
b1 9
b10 C
b10 /
b10 @
b10 7
b1 '
b11111111111111111111111111111111 -
b1 .
b1 +
1(
1&
b110 %
b1000010 )
b1000010 0
b1000010 4
b1000010 ,
#670
b11 C
b11 /
b11 @
b11 7
b11111111111111111111111111111111 -
b1 .
b1 +
1(
1&
b1 '
b110 %
b1000011 )
b1000011 0
b1000011 4
b1000011 ,
#680
b10 "
b10 1
b10 B
b10 E
b10 9
b100 C
b100 /
b100 @
b100 7
b11111111111111111111111111111111 -
b1 .
b1 +
1(
1&
b10 '
b110 %
b1000100 )
b1000100 0
b1000100 4
b1000100 ,
#690
b101 C
b101 /
b101 @
b101 7
b11111111111111111111111111111111 -
b1 .
b1 +
1(
1&
b10 '
b110 %
b1000101 )
b1000101 0
b1000101 4
b1000101 ,
#700
b110 C
b110 /
b110 @
b110 7
b11111111111111111111111111111111 -
b1 .
b1 +
1(
1&
b10 '
b110 %
b1000110 )
b1000110 0
b1000110 4
b1000110 ,
#710
b111 C
b111 /
b111 @
b111 7
b11111111111111111111111111111111 -
b1 .
b1 +
1(
1&
b10 '
b110 %
b1000111 )
b1000111 0
b1000111 4
b1000111 ,
#720
b11 "
b11 1
b11 B
b11 E
b11 9
b1000 C
b1000 /
b1000 @
b1000 7
b11111111111111111111111111111111 -
b1 .
b1 +
1(
1&
b11 '
b110 %
b1001000 )
b1001000 0
b1001000 4
b1001000 ,
#730
b1001 C
b1001 /
b1001 @
b1001 7
b11111111111111111111111111111111 -
b1 .
b1 +
1(
1&
b11 '
b110 %
b1001001 )
b1001001 0
b1001001 4
b1001001 ,
#740
b1010 C
b1010 /
b1010 @
b1010 7
b11111111111111111111111111111111 -
b1 .
b1 +
1(
1&
b11 '
b110 %
b1001010 )
b1001010 0
b1001010 4
b1001010 ,
#750
b1011 C
b1011 /
b1011 @
b1011 7
b11111111111111111111111111111111 -
b1 .
b1 +
1(
1&
b11 '
b110 %
b1001011 )
b1001011 0
b1001011 4
b1001011 ,
#760
b1100 C
b1100 /
b1100 @
b1100 7
b11111111111111111111111111111111 -
b1 .
b1 +
1(
1&
b11 '
b110 %
b1001100 )
b1001100 0
b1001100 4
b1001100 ,
#770
b1101 C
b1101 /
b1101 @
b1101 7
b11111111111111111111111111111111 -
b1 .
b1 +
1(
1&
b11 '
b110 %
b1001101 )
b1001101 0
b1001101 4
b1001101 ,
#780
b1110 C
b1110 /
b1110 @
b1110 7
b11111111111111111111111111111111 -
b1 .
b1 +
1(
1&
b11 '
b110 %
b1001110 )
b1001110 0
b1001110 4
b1001110 ,
#790
b1111 C
b1111 /
b1111 @
b1111 7
b11111111111111111111111111111111 -
b1 .
b1 +
1(
1&
b11 '
b110 %
b1001111 )
b1001111 0
b1001111 4
b1001111 ,
#800
b100 "
b100 1
b100 B
b0 E
b10 A
b0 9
0D
b0 C
1G
b1 F
b10 5
b10000 /
b10000 @
08
b0 7
b101 :
b11111111111111111111111111111111 -
b1 .
b1 +
1(
1&
b100 '
b110 %
b1010000 )
b1010000 0
b1010000 4
b1010000 ,
#810
b11 A
1D
b1 C
b11 5
b10001 /
b10001 @
18
b1 7
b11111111111111111111111111111111 -
b1 .
b1 +
1(
1&
b100 '
b110 %
b1010001 )
b1010001 0
b1010001 4
b1010001 ,
#820
b1 E
b1 9
b10 C
b10010 /
b10010 @
b10 7
b11111111111111111111111111111111 -
b1 .
b1 +
1(
1&
b100 '
b110 %
b1010010 )
b1010010 0
b1010010 4
b1010010 ,
#830
b11 C
b10011 /
b10011 @
b11 7
b11111111111111111111111111111111 -
b1 .
b1 +
1(
1&
b100 '
b110 %
b1010011 )
b1010011 0
b1010011 4
b1010011 ,
#840
b10 E
b10 9
b100 C
b10100 /
b10100 @
b100 7
b11111111111111111111111111111111 -
b1 .
b1 +
1(
1&
b100 '
b110 %
b1010100 )
b1010100 0
b1010100 4
b1010100 ,
#850
b101 C
b10101 /
b10101 @
b101 7
b11111111111111111111111111111111 -
b1 .
b1 +
1(
1&
b100 '
b110 %
b1010101 )
b1010101 0
b1010101 4
b1010101 ,
#860
b110 C
b10110 /
b10110 @
b110 7
b11111111111111111111111111111111 -
b1 .
b1 +
1(
1&
b100 '
b110 %
b1010110 )
b1010110 0
b1010110 4
b1010110 ,
#870
b111 C
b10111 /
b10111 @
b111 7
b11111111111111111111111111111111 -
b1 .
b1 +
1(
1&
b100 '
b110 %
b1010111 )
b1010111 0
b1010111 4
b1010111 ,
#880
b11 E
b11 9
b1000 C
b11000 /
b11000 @
b1000 7
b11111111111111111111111111111111 -
b1 .
b1 +
1(
1&
b100 '
b110 %
b1011000 )
b1011000 0
b1011000 4
b1011000 ,
#890
b1001 C
b11001 /
b11001 @
b1001 7
b11111111111111111111111111111111 -
b1 .
b1 +
1(
1&
b100 '
b110 %
b1011001 )
b1011001 0
b1011001 4
b1011001 ,
#900
b1010 C
b11010 /
b11010 @
b1010 7
b11111111111111111111111111111111 -
b1 .
b1 +
1(
1&
b100 '
b110 %
b1011010 )
b1011010 0
b1011010 4
b1011010 ,
#910
b1011 C
b11011 /
b11011 @
b1011 7
b11111111111111111111111111111111 -
b1 .
b1 +
1(
1&
b100 '
b110 %
b1011011 )
b1011011 0
b1011011 4
b1011011 ,
#920
b1100 C
b11100 /
b11100 @
b1100 7
b11111111111111111111111111111111 -
b1 .
b1 +
1(
1&
b100 '
b110 %
b1011100 )
b1011100 0
b1011100 4
b1011100 ,
#930
b1101 C
b11101 /
b11101 @
b1101 7
b11111111111111111111111111111111 -
b1 .
b1 +
1(
1&
b100 '
b110 %
b1011101 )
b1011101 0
b1011101 4
b1011101 ,
#940
b1110 C
b11110 /
b11110 @
b1110 7
b11111111111111111111111111111111 -
b1 .
b1 +
1(
1&
b100 '
b110 %
b1011110 )
b1011110 0
b1011110 4
b1011110 ,
#950
b1111 C
b11111 /
b11111 @
b1111 7
b11111111111111111111111111111111 -
b1 .
b1 +
1(
1&
b100 '
b110 %
b1011111 )
b1011111 0
b1011111 4
b1011111 ,
#960
b101 "
b101 1
b101 B
b1 H
b0 E
b10 A
b0 9
0D
b0 C
b10 F
b10 5
b100000 /
b100000 @
08
b0 7
b110 :
b11111111111111111111111111111111 -
b1 .
b1 +
1(
1&
b101 '
b110 %
b1100000 )
b1100000 0
b1100000 4
b1100000 ,
#970
b11 A
1D
b1 C
b11 5
b100001 /
b100001 @
18
b1 7
b11111111111111111111111111111111 -
b1 .
b1 +
1(
1&
b101 '
b110 %
b1100001 )
b1100001 0
b1100001 4
b1100001 ,
#980
b1 E
b1 9
b10 C
b100010 /
b100010 @
b10 7
b11111111111111111111111111111111 -
b1 .
b1 +
1(
1&
b101 '
b110 %
b1100010 )
b1100010 0
b1100010 4
b1100010 ,
#990
b11 C
b100011 /
b100011 @
b11 7
b11111111111111111111111111111111 -
b1 .
b1 +
1(
1&
b101 '
b110 %
b1100011 )
b1100011 0
b1100011 4
b1100011 ,
#1000
b10 E
b10 9
b100 C
b100100 /
b100100 @
b100 7
b11111111111111111111111111111111 -
b1 .
b1 +
1(
1&
b101 '
b110 %
b1100100 )
b1100100 0
b1100100 4
b1100100 ,
#1010
b101 C
b100101 /
b100101 @
b101 7
b11111111111111111111111111111111 -
b1 .
b1 +
1(
1&
b101 '
b110 %
b1100101 )
b1100101 0
b1100101 4
b1100101 ,
#1020
b110 C
b100110 /
b100110 @
b110 7
b11111111111111111111111111111111 -
b1 .
b1 +
1(
1&
b101 '
b110 %
b1100110 )
b1100110 0
b1100110 4
b1100110 ,
#1030
b111 C
b100111 /
b100111 @
b111 7
b11111111111111111111111111111111 -
b1 .
b1 +
1(
1&
b101 '
b110 %
b1100111 )
b1100111 0
b1100111 4
b1100111 ,
#1040
b11 E
b11 9
b1000 C
b101000 /
b101000 @
b1000 7
b11111111111111111111111111111111 -
b1 .
b1 +
1(
1&
b101 '
b110 %
b1101000 )
b1101000 0
b1101000 4
b1101000 ,
#1050
b1001 C
b101001 /
b101001 @
b1001 7
b11111111111111111111111111111111 -
b1 .
b1 +
1(
1&
b101 '
b110 %
b1101001 )
b1101001 0
b1101001 4
b1101001 ,
#1060
b1010 C
b101010 /
b101010 @
b1010 7
b11111111111111111111111111111111 -
b1 .
b1 +
1(
1&
b101 '
b110 %
b1101010 )
b1101010 0
b1101010 4
b1101010 ,
#1070
b1011 C
b101011 /
b101011 @
b1011 7
b11111111111111111111111111111111 -
b1 .
b1 +
1(
1&
b101 '
b110 %
b1101011 )
b1101011 0
b1101011 4
b1101011 ,
#1080
b1100 C
b101100 /
b101100 @
b1100 7
b11111111111111111111111111111111 -
b1 .
b1 +
1(
1&
b101 '
b110 %
b1101100 )
b1101100 0
b1101100 4
b1101100 ,
#1090
b1101 C
b101101 /
b101101 @
b1101 7
b11111111111111111111111111111111 -
b1 .
b1 +
1(
1&
b101 '
b110 %
b1101101 )
b1101101 0
b1101101 4
b1101101 ,
#1100
b1110 C
b101110 /
b101110 @
b1110 7
b11111111111111111111111111111111 -
b1 .
b1 +
1(
1&
b101 '
b110 %
b1101110 )
b1101110 0
b1101110 4
b1101110 ,
#1110
b1111 C
b101111 /
b101111 @
b1111 7
b11111111111111111111111111111111 -
b1 .
b1 +
1(
1&
b101 '
b110 %
b1101111 )
b1101111 0
b1101111 4
b1101111 ,
#1120
b0 E
b10 A
b0 9
0D
b0 C
b11 F
b10 5
b110000 /
b110000 @
08
b0 7
b111 :
b11111111111111111111111111111111 -
b1 .
b1 +
1(
1&
b101 '
b110 %
b1110000 )
b1110000 0
b1110000 4
b1110000 ,
#1130
b11 A
1D
b1 C
b11 5
b110001 /
b110001 @
18
b1 7
b11111111111111111111111111111111 -
b1 .
b1 +
1(
1&
b101 '
b110 %
b1110001 )
b1110001 0
b1110001 4
b1110001 ,
#1140
b1 E
b1 9
b10 C
b110010 /
b110010 @
b10 7
b11111111111111111111111111111111 -
b1 .
b1 +
1(
1&
b101 '
b110 %
b1110010 )
b1110010 0
b1110010 4
b1110010 ,
#1150
b11 C
b110011 /
b110011 @
b11 7
b11111111111111111111111111111111 -
b1 .
b1 +
1(
1&
b101 '
b110 %
b1110011 )
b1110011 0
b1110011 4
b1110011 ,
#1160
b10 E
b10 9
b100 C
b110100 /
b110100 @
b100 7
b11111111111111111111111111111111 -
b1 .
b1 +
1(
1&
b101 '
b110 %
b1110100 )
b1110100 0
b1110100 4
b1110100 ,
#1170
b101 C
b110101 /
b110101 @
b101 7
b11111111111111111111111111111111 -
b1 .
b1 +
1(
1&
b101 '
b110 %
b1110101 )
b1110101 0
b1110101 4
b1110101 ,
#1180
b110 C
b110110 /
b110110 @
b110 7
b11111111111111111111111111111111 -
b1 .
b1 +
1(
1&
b101 '
b110 %
b1110110 )
b1110110 0
b1110110 4
b1110110 ,
#1190
b111 C
b110111 /
b110111 @
b111 7
b11111111111111111111111111111111 -
b1 .
b1 +
1(
1&
b101 '
b110 %
b1110111 )
b1110111 0
b1110111 4
b1110111 ,
